fmtlabels/__init__.py
fmtlabels/fmt.py
fmtlabels/lines.py
fmtlabels/tab.py
fmtlabels-0.4.3.data/scripts/cntaspect
fmtlabels-0.4.3.data/scripts/fmtlines
fmtlabels-0.4.3.data/scripts/fmttab
fmtlabels-0.4.3.dist-info/DESCRIPTION.rst
fmtlabels-0.4.3.dist-info/METADATA
fmtlabels-0.4.3.dist-info/RECORD
fmtlabels-0.4.3.dist-info/WHEEL
fmtlabels-0.4.3.dist-info/metadata.json
fmtlabels-0.4.3.dist-info/top_level.txt
